<annotation>
	<folder>1</folder>
	<filename>67.jpg</filename>
	<path>D:\apps\labelimg_windows_v1.7.0\images\resized_imaged\1\67.jpg</path>
	<source>
		<database>Unknown</database>
	</source>
	<size>
		<width>1024</width>
		<height>640</height>
		<depth>3</depth>
	</size>
	<segmented>0</segmented>
	<object>
		<name>button</name>
		<pose>Unspecified</pose>
		<truncated>0</truncated>
		<difficult>0</difficult>
		<bndbox>
			<xmin>334</xmin>
			<ymin>485</ymin>
			<xmax>688</xmax>
			<ymax>539</ymax>
		</bndbox>
	</object>
	<object>
		<name>label_SignIn</name>
		<pose>Unspecified</pose>
		<truncated>0</truncated>
		<difficult>0</difficult>
		<bndbox>
			<xmin>416</xmin>
			<ymin>493</ymin>
			<xmax>602</xmax>
			<ymax>531</ymax>
		</bndbox>
	</object>
	<object>
		<name>textbox</name>
		<pose>Unspecified</pose>
		<truncated>0</truncated>
		<difficult>0</difficult>
		<bndbox>
			<xmin>243</xmin>
			<ymin>362</ymin>
			<xmax>848</xmax>
			<ymax>421</ymax>
		</bndbox>
	</object>
	<object>
		<name>textbox</name>
		<pose>Unspecified</pose>
		<truncated>0</truncated>
		<difficult>0</difficult>
		<bndbox>
			<xmin>240</xmin>
			<ymin>202</ymin>
			<xmax>849</xmax>
			<ymax>258</ymax>
		</bndbox>
	</object>
	<object>
		<name>label_password</name>
		<pose>Unspecified</pose>
		<truncated>0</truncated>
		<difficult>0</difficult>
		<bndbox>
			<xmin>385</xmin>
			<ymin>305</ymin>
			<xmax>634</xmax>
			<ymax>345</ymax>
		</bndbox>
	</object>
	<object>
		<name>label_Username</name>
		<pose>Unspecified</pose>
		<truncated>0</truncated>
		<difficult>0</difficult>
		<bndbox>
			<xmin>383</xmin>
			<ymin>155</ymin>
			<xmax>646</xmax>
			<ymax>192</ymax>
		</bndbox>
	</object>
	<object>
		<name>label_Login</name>
		<pose>Unspecified</pose>
		<truncated>0</truncated>
		<difficult>0</difficult>
		<bndbox>
			<xmin>388</xmin>
			<ymin>39</ymin>
			<xmax>637</xmax>
			<ymax>101</ymax>
		</bndbox>
	</object>
	<object>
		<name>button_SignIn</name>
		<pose>Unspecified</pose>
		<truncated>0</truncated>
		<difficult>0</difficult>
		<bndbox>
			<xmin>335</xmin>
			<ymin>486</ymin>
			<xmax>690</xmax>
			<ymax>543</ymax>
		</bndbox>
	</object>
</annotation>
